Workbook

Sheet Fixos
A1: Custo Fixos
A2: Item | B2: Valor
A3: Api TMDB | B3: 0
A4: Hospedagem | B4: 30
A5: Dominio | B5: 3

Sheet Premissas
A1: PREMISSAS DO NEGÓCIO
A2: Premissa | B2: Valor (editável)
A3: Ticket médio (R$) | B3: 5
A4: CAC — Custo por Cliente | B4: 10
A5: Churn mensal | B5: 0.07
A6: Custos fixos/mês (R$) | B6: =SUM(Fixos!$B$3:$B$30) -> 33
A7: Crescimento mensal ( organico ) | B7: 0.2
A9: UNIT ECONOMICS
A10: Métrica | B10: Valor
A11: Custo Ticket | B11: 0.8
A12: Margem de Contribuição | B12: =B3-B11 -> 4.2
A13: Margem % | B13: =100% - (B11/B3) -> 0.84
A14: LTV | B14: =B3/B5 -> 71.428571
A15: LTV/CAC | B15: =(B3/B5)/B4 -> 7.1428571
A16: Payback CAC (meses) | B16: =B4/B3 -> 2
A17: Break-even (clientes) | B17: =B6/(B3-(B3*0.15)) -> 7.7647059

Sheet Projeção
A1: CENÁRIO PESSIMISTA
A2: Mês | B2: Novos | C2: Churn | D2: Base Ativa | E2: Receita | F2: Marketing Pago | G2: Fixos | H2: Variáveis | I2: Total Despesas | J2: Resultado | K2: Acumulado
A3: 6 | B3: =F3/Premissas!$B$4 -> 50 | C3: 0 | D3: =B3-C3 -> 50 | E3: =D3*Premissas!$B$3 -> 250 | F3: 500 | G3: =Premissas!$B$6 -> 33 | H3: =E3*(Premissas!$B$11/Premissas!$B$3) -> 40 | I3: =F3+G3+H3 -> 573 | J3: =E3-I3 -> -323 | K3: =J3 -> -323
A4: 7 | B4: =ROUND(D3*Premissas!$B$7*0.6,0) + (F4/Premissas!$B$4) -> 56 | C4: =ROUND(D3*Premissas!$B$5*0.6,0) -> 2 | D4: =D3+B4-C4 -> 104 | E4: =D4*Premissas!$B$3 -> 520 | F4: 500 | G4: =Premissas!$B$6 -> 33 | H4: =E4*(Premissas!$B$11/Premissas!$B$3) -> 83.2 | I4: =F4+G4+H4 -> 616.2 | J4: =E4-I4 -> -96.2 | K4: =K3+J4 -> -419.2
A5: 8 | B5: =ROUND(D4*Premissas!$B$7*0.6,0) + (F5/Premissas!$B$4) -> 62 | C5: =ROUND(D4*Premissas!$B$5*0.6,0) -> 4 | D5: =D4+B5-C5 -> 162 | E5: =D5*Premissas!$B$3 -> 810 | F5: 500 | G5: =Premissas!$B$6 -> 33 | H5: =E5*(Premissas!$B$11/Premissas!$B$3) -> 129.6 | I5: =F5+G5+H5 -> 662.6 | J5: =E5-I5 -> 147.4 | K5: =K4+J5 -> -271.8
A6: 9 | B6: =ROUND(D5*Premissas!$B$7*0.6,0) + (F6/Premissas!$B$4) -> 69 | C6: =ROUND(D5*Premissas!$B$5*0.6,0) -> 7 | D6: =D5+B6-C6 -> 224 | E6: =D6*Premissas!$B$3 -> 1120 | F6: 500 | G6: =Premissas!$B$6 -> 33 | H6: =E6*(Premissas!$B$11/Premissas!$B$3) -> 179.2 | I6: =F6+G6+H6 -> 712.2 | J6: =E6-I6 -> 407.8 | K6: =K5+J6 -> 136
A7: 10 | B7: =ROUND(D6*Premissas!$B$7*0.6,0) + (F7/Premissas!$B$4) -> 77 | C7: =ROUND(D6*Premissas!$B$5*0.6,0) -> 9 | D7: =D6+B7-C7 -> 292 | E7: =D7*Premissas!$B$3 -> 1460 | F7: 500 | G7: =Premissas!$B$6 -> 33 | H7: =E7*(Premissas!$B$11/Premissas!$B$3) -> 233.6 | I7: =F7+G7+H7 -> 766.6 | J7: =E7-I7 -> 693.4 | K7: =K6+J7 -> 829.4
A8: 11 | B8: =ROUND(D7*Premissas!$B$7*0.6,0) + (F8/Premissas!$B$4) -> 135 | C8: =ROUND(D7*Premissas!$B$5*0.6,0) -> 12 | D8: =D7+B8-C8 -> 415 | E8: =D8*Premissas!$B$3 -> 2075 | F8: 1000 | G8: =Premissas!$B$6 -> 33 | H8: =E8*(Premissas!$B$11/Premissas!$B$3) -> 332 | I8: =F8+G8+H8 -> 1365 | J8: =E8-I8 -> 710 | K8: =K7+J8 -> 1539.4
A9: 12 | B9: =ROUND(D8*Premissas!$B$7*0.6,0) + (F9/Premissas!$B$4) -> 150 | C9: =ROUND(D8*Premissas!$B$5*0.6,0) -> 17 | D9: =D8+B9-C9 -> 548 | E9: =D9*Premissas!$B$3 -> 2740 | F9: 1000 | G9: =Premissas!$B$6 -> 33 | H9: =E9*(Premissas!$B$11/Premissas!$B$3) -> 438.4 | I9: =F9+G9+H9 -> 1471.4 | J9: =E9-I9 -> 1268.6 | K9: =K8+J9 -> 2808
A10: 1 | B10: =ROUND(D9*Premissas!$B$7*0.6,0) + (F10/Premissas!$B$4) -> 166 | C10: =ROUND(D9*Premissas!$B$5*0.6,0) -> 23 | D10: =D9+B10-C10 -> 691 | E10: =D10*Premissas!$B$3 -> 3455 | F10: 1000 | G10: =Premissas!$B$6 -> 33 | H10: =E10*(Premissas!$B$11/Premissas!$B$3) -> 552.8 | I10: =F10+G10+H10 -> 1585.8 | J10: =E10-I10 -> 1869.2 | K10: =K9+J10 -> 4677.2
A11: 2 | B11: =ROUND(D10*Premissas!$B$7*0.6,0) + (F11/Premissas!$B$4) -> 183 | C11: =ROUND(D10*Premissas!$B$5*0.6,0) -> 29 | D11: =D10+B11-C11 -> 845 | E11: =D11*Premissas!$B$3 -> 4225 | F11: 1000 | G11: =Premissas!$B$6 -> 33 | H11: =E11*(Premissas!$B$11/Premissas!$B$3) -> 676 | I11: =F11+G11+H11 -> 1709 | J11: =E11-I11 -> 2516 | K11: =K10+J11 -> 7193.2
A12: 3 | B12: =ROUND(D11*Premissas!$B$7*0.6,0) + (F12/Premissas!$B$4) -> 301 | C12: =ROUND(D11*Premissas!$B$5*0.6,0) -> 35 | D12: =D11+B12-C12 -> 1111 | E12: =D12*Premissas!$B$3 -> 5555 | F12: 2000 | G12: =Premissas!$B$6 -> 33 | H12: =E12*(Premissas!$B$11/Premissas!$B$3) -> 888.8 | I12: =F12+G12+H12 -> 2921.8 | J12: =E12-I12 -> 2633.2 | K12: =K11+J12 -> 9826.4
A13: 4 | B13: =ROUND(D12*Premissas!$B$7*0.6,0) + (F13/Premissas!$B$4) -> 333 | C13: =ROUND(D12*Premissas!$B$5*0.6,0) -> 47 | D13: =D12+B13-C13 -> 1397 | E13: =D13*Premissas!$B$3 -> 6985 | F13: 2000 | G13: =Premissas!$B$6 -> 33 | H13: =E13*(Premissas!$B$11/Premissas!$B$3) -> 1117.6 | I13: =F13+G13+H13 -> 3150.6 | J13: =E13-I13 -> 3834.4 | K13: =K12+J13 -> 13660.8
A14: 5 | B14: =ROUND(D13*Premissas!$B$7*0.6,0) + (F14/Premissas!$B$4) -> 368 | C14: =ROUND(D13*Premissas!$B$5*0.6,0) -> 59 | D14: =D13+B14-C14 -> 1706 | E14: =D14*Premissas!$B$3 -> 8530 | F14: 2000 | G14: =Premissas!$B$6 -> 33 | H14: =E14*(Premissas!$B$11/Premissas!$B$3) -> 1364.8 | I14: =F14+G14+H14 -> 3397.8 | J14: =E14-I14 -> 5132.2 | K14: =K13+J14 -> 18793
A15: 6 | B15: =ROUND(D14*Premissas!$B$7*0.6,0) + (F15/Premissas!$B$4) -> 405 | C15: =ROUND(D14*Premissas!$B$5*0.6,0) -> 72 | D15: =D14+B15-C15 -> 2039 | E15: =D15*Premissas!$B$3 -> 10195 | F15: 2000 | G15: =Premissas!$B$6 -> 33 | H15: =E15*(Premissas!$B$11/Premissas!$B$3) -> 1631.2 | I15: =F15+G15+H15 -> 3664.2 | J15: =E15-I15 -> 6530.8 | K15: =K14+J15 -> 25323.8
... A21: 12 | B21: =ROUND(D20*Premissas!$B$7*0.6,0) + (F21/Premissas!$B$4) -> 1005 | C21: =ROUND(D20*Premissas!$B$5*0.6,0) -> 212 | D21: =D20+B21-C21 -> 5838 | E21: =D21*Premissas!$B$3 -> 29190 | F21: 4000 | G21: =Premissas!$B$6 -> 33 | H21: =E21*(Premissas!$B$11/Premissas!$B$3) -> 4670.4 | I21: =F21+G21+H21 -> 8703.4 | J21: =E21-I21 -> 20486.6 | K21: =K20+J21 -> 105223.6
B22: =ROUND(D21*Premissas!$B$7*0.6,0) + (F22/Premissas!$B$4) -> 1101 | C22: =ROUND(D21*Premissas!$B$5*0.6,0) -> 245 | D22: =D21+B22-C22 -> 6694 | E22: =D22*Premissas!$B$3 -> 33470 | F22: 4000 | G22: =Premissas!$B$6 -> 33 | H22: =E22*(Premissas!$B$11/Premissas!$B$3) -> 5355.2 | I22: =F22+G22+H22 -> 9388.2 | J22: =E22-I22 -> 24081.8 | K22: =K21+J22 -> 129305.4
B23: =ROUND(D22*Premissas!$B$7*0.6,0) + (F23/Premissas!$B$4) -> 1203 | C23: =ROUND(D22*Premissas!$B$5*0.6,0) -> 281 | D23: =D22+B23-C23 -> 7616 | E23: =D23*Premissas!$B$3 -> 38080 | F23: 4000 | G23: =Premissas!$B$6 -> 33 | H23: =E23*(Premissas!$B$11/Premissas!$B$3) -> 6092.8 | I23: =F23+G23+H23 -> 10125.8 | J23: =E23-I23 -> 27954.2 | K23: =K22+J23 -> 157259.6
B24: =ROUND(D23*Premissas!$B$7*0.6,0) + (F24/Premissas!$B$4) -> 1314 | C24: =ROUND(D23*Premissas!$B$5*0.6,0) -> 320 | D24: =D23+B24-C24 -> 8610 | E24: =D24*Premissas!$B$3 -> 43050 | F24: 4000 | G24: =Premissas!$B$6 -> 33 | H24: =E24*(Premissas!$B$11/Premissas!$B$3) -> 6888 | I24: =F24+G24+H24 -> 10921 | J24: =E24-I24 -> 32129 | K24: =K23+J24 -> 189388.6
B25: =ROUND(D24*Premissas!$B$7*0.6,0) + (F25/Premissas!$B$4) -> 1433 | C25: =ROUND(D24*Premissas!$B$5*0.6,0) -> 362 | D25: =D24+B25-C25 -> 9681 | E25: =D25*Premissas!$B$3 -> 48405 | F25: 4000 | G25: =Premissas!$B$6 -> 33 | H25: =E25*(Premissas!$B$11/Premissas!$B$3) -> 7744.8 | I25: =F25+G25+H25 -> 11777.8 | J25: =E25-I25 -> 36627.2 | K25: =K24+J25 -> 226015.8
B26: =ROUND(D25*Premissas!$B$7*0.6,0) + (F26/Premissas!$B$4) -> 1562 | C26: =ROUND(D25*Premissas!$B$5*0.6,0) -> 407 | D26: =D25+B26-C26 -> 10836 | E26: =D26*Premissas!$B$3 -> 54180 | F26: 4000 | G26: =Premissas!$B$6 -> 33 | H26: =E26*(Premissas!$B$11/Premissas!$B$3) -> 8668.8 | I26: =F26+G26+H26 -> 12701.8 | J26: =E26-I26 -> 41478.2 | K26: =K25+J26 -> 267494
A27: TOTAL | E27: =SUM(E3:E26) -> 386650 | F27: =SUM(F3:F26) -> 56500 | G27: =SUM(G3:G26) -> 792 | H27: =SUM(H3:H26) -> 61864 | I27: =SUM(I3:I26) -> 119156 | J27: =SUM(J3:J26) -> 267494
